{"features":[
	{"geometry":{"coordinates":[-1.6417472,53.8364399],"type":"Point"},"properties":{"amenity":"charging_station","osm_id":"8365687073","other_tags":{"capacity":"3","fee":"no","operator":"Pod Point","website":"https://pod-point.com/"}},"type":"Feature"}
],"type":"FeatureCollection","last_updated":"2023-02-05T21:21:25Z"}