{"features":[
	{"geometry":{"coordinates":[-1.6419201,53.8372232],"type":"Point"},"properties":{"name":"Althams travel","osm_id":"3886297906","other_tags":{"addr:city":"Leeds","addr:housenumber":"17","addr:postcode":"LS18 4RJ","addr:street":"Town Street","addr:suburb":"Horsforth","opening_hours":"Mo-Sa 09:30-17:00","shop":"travel_agency"}},"type":"Feature"},
	{"geometry":{"coordinates":[-1.6393277,53.8385936],"type":"Point"},"properties":{"name":"Hays Travel","osm_id":"3887782348","other_tags":{"addr:city":"Leeds","addr:housenumber":"70","addr:postcode":"LS18 4AP","addr:street":"Town Street","addr:suburb":"Horsforth","brand":"Hays Travel","brand:wikidata":"Q70250954","brand:wikipedia":"en:Hays Travel","opening_hours":"Su off; Mo-Fr 09:15-17:30; Sa 09:15-17:00","phone":"+44 844 335 7420","shop":"travel_agency"}},"type":"Feature"},
	{"geometry":{"coordinates":[-1.6378422,53.8396413],"type":"Point"},"properties":{"name":"Holidays By Design","osm_id":"3887789760","other_tags":{"addr:city":"Leeds","addr:housenumber":"102","addr:postcode":"LS18 4AP","addr:street":"Town Street","addr:suburb":"Horsforth","opening_hours":"Tu-Sa 10:00-17:00","shop":"travel_agency"}},"type":"Feature"},
	{"geometry":{"coordinates":[-1.6479575,53.8332855],"type":"Point"},"properties":{"name":"Company Travel Ltd","osm_id":"3900193757","other_tags":{"addr:city":"Leeds","addr:housenumber":"253","addr:postcode":"LS18 4DR","addr:street":"New Road Side","addr:suburb":"Horsforth","phone":"+44 113 2590266","shop":"travel_agency","website":"http://www.companytravelltd.co.uk/"}},"type":"Feature"}
],"type":"FeatureCollection"}